{
   "agg":[
      [
         "attigneenongnahac"
      ],
      0,
      0
   ],
   "abe":[
      [
         "abenaki"
      ],
      0,
      0
   ],
   "afa":[
      [
         "aussa"
      ],
      0,
      0
   ],
   "kgr":[
      [
         "kangra"
      ],
      0,
      0
   ],
   "vrn":[
      [
         "verona"
      ],
      0,
      0
   ],
   "che":[
      [
         "cherokee"
      ],
      1515,
      583
   ],
   "kln":[
      [
         "keladi"
      ],
      0,
      0
   ],
   "koh":[
      [
         "koho"
      ],
      0,
      0
   ],
   "mks":[
      [
         "makassar"
      ],
      0,
      0
   ],
   "mma":[
      [
         "mongmao"
      ],
      0,
      0
   ],
   "akm":[
      [
         "akamatsu"
      ],
      0,
      0
   ],
   "nvk":[
      [
         "nivkh"
      ],
      0,
      0
   ],
   "ing":[
      [
         "ingolstadt"
      ],
      0,
      0
   ],
   "bht":[
      [
         "soran"
      ],
      0,
      0
   ],
   "caq":[
      [
         "casqui"
      ],
      0,
      0
   ],
   "kno":[
      [
         "kono"
      ],
      0,
      0
   ],
   "buk":[
      [
         "bukhara"
      ],
      0,
      0
   ],
   "sfa":[
      [
         "sofala"
      ],
      0,
      0
   ],
   "wbg":[
      [
         "wurzburg"
      ],
      0,
      0
   ],
   "tsc":[
      [
         "tuscarora"
      ],
      0,
      0
   ],
   "cub":[
      [
         "cuba"
      ],
      0,
      0
   ],
   "tid":[
      [
         "tidore"
      ],
      0,
      0
   ],
   "kaz":[
      [
         "kazan"
      ],
      3489,
      453
   ],
   "tnt":[
      [
         "trent"
      ],
      0,
      0
   ],
   "lak":[
      [
         "lakota"
      ],
      0,
      0
   ],
   "cay":[
      [
         "cayuga"
      ],
      0,
      0
   ],
   "shy":[
      [
         "uzbek"
      ],
      3876,
      560
   ],
   "ton":[
      [
         "tonallan"
      ],
      0,
      0
   ],
   "gng":[
      [
         "gingee"
      ],
      0,
      0
   ],
   "stk":[
      [
         "satake"
      ],
      0,
      0
   ],
   "guy":[
      [
         "gascony"
      ],
      0,
      0
   ],
   "opl":[
      [
         "opole"
      ],
      0,
      0
   ],
   "eto":[
      [
         "etowah"
      ],
      0,
      0
   ],
   "man":[
      [
         "mantua"
      ],
      2973,
      626
   ],
   "mra":[
      [
         "maravi"
      ],
      0,
      0
   ],
   "prd":[
      [
         "parlakhimidi"
      ],
      0,
      0
   ],
   "jai":[
      [
         "malta"
      ],
      0,
      0
   ],
   "ymn":[
      [
         "yamana"
      ],
      4902,
      816
   ],
   "mau":[
      [
         "maui"
      ],
      0,
      0
   ],
   "ark":[
      [
         "arakan"
      ],
      0,
      0
   ],
   "son":[
      [
         "songhai"
      ],
      2835,
      1160
   ],
   "pic":[
      [
         "picardy"
      ],
      0,
      0
   ],
   "nah":[
      [
         "navajo"
      ],
      0,
      0
   ],
   "sen":[
      [
         "seneca"
      ],
      0,
      0
   ],
   "loi":[
      [
         "the_isles"
      ],
      2702,
      356
   ],
   "med":[
      [
         "medri bahri"
      ],
      0,
      0
   ],
   "pgr":[
      [
         "pagarruyung"
      ],
      0,
      0
   ],
   "slz":[
      [
         "salzburg"
      ],
      0,
      0
   ],
   "gos":[
      [
         "goslar"
      ],
      0,
      0
   ],
   "hab":[
      [
         "austria"
      ],
      3031,
      586
   ],
   "mca":[
      [
         "muisca"
      ],
      0,
      0
   ],
   "tok":[
      [
         "tonkin"
      ],
      0,
      0
   ],
   "jnn":[
      [
         "jenn\u00c3\u00a9"
      ],
      0,
      0
   ],
   "mya":[
      [
         "mong yang"
      ],
      0,
      0
   ],
   "yak":[
      [
         "yaka"
      ],
      0,
      0
   ],
   "wes":[
      [
         "westphalia"
      ],
      0,
      0
   ],
   "#trl":[
      [
         "trapalanda"
      ],
      0,
      0
   ],
   "brt":[
      [
         "buryatia"
      ],
      0,
      0
   ],
   "oah":[
      [
         "oahu"
      ],
      0,
      0
   ],
   "koc":[
      [
         "kochin"
      ],
      0,
      0
   ],
   "blm":[
      [
         "blambangan"
      ],
      0,
      0
   ],
   "dec":[
      [
         "deccan"
      ],
      0,
      0
   ],
   "jap":[
      [
         "japan"
      ],
      4929,
      816
   ],
   "tve":[
      [
         "tver"
      ],
      0,
      0
   ],
   "htk":[
      [
         "hatakeyama"
      ],
      0,
      0
   ],
   "dul":[
      [
         "dulkadir"
      ],
      3380,
      755
   ],
   "sco":[
      [
         "scotland"
      ],
      2743,
      385
   ],
   "cua":[
      [
         "charrua"
      ],
      0,
      0
   ],
   "tpr":[
      [
         "tripura"
      ],
      0,
      0
   ],
   "lon":[
      [
         "le\u00c3\u00b3n"
      ],
      0,
      0
   ],
   "frn":[
      [
         "frankfurt"
      ],
      2945,
      526
   ],
   "fza":[
      [
         "fezzan"
      ],
      0,
      0
   ],
   "kam":[
      [
         "kham"
      ],
      0,
      0
   ],
   "aac":[
      [
         "aachen"
      ],
      2904,
      516
   ],
   "trp":[
      [
         "tripoli"
      ],
      0,
      0
   ],
   "rso":[
      [
         "rostov"
      ],
      0,
      0
   ],
   "peo":[
      [
         "peoria"
      ],
      0,
      0
   ],
   "kaa":[
      [
         "kauai"
      ],
      0,
      0
   ],
   "bou":[
      [
         "bourbonnais"
      ],
      0,
      0
   ],
   "wai":[
      [
         "waitaha"
      ],
      0,
      0
   ],
   "hdy":[
      [
         "hadiya"
      ],
      0,
      0
   ],
   "urb":[
      [
         "urbino"
      ],
      0,
      0
   ],
   "ala":[
      [
         "alaska"
      ],
      0,
      0
   ],
   "tir":[
      [
         "tirol"
      ],
      0,
      0
   ],
   "hun":[
      [
         "hungary"
      ],
      3135,
      597
   ],
   "czh":[
      [
         "zhou"
      ],
      0,
      0
   ],
   "lub":[
      [
         "luba"
      ],
      0,
      0
   ],
   "ghd":[
      [
         "djerid"
      ],
      0,
      0
   ],
   "isl":[
      [
         "isleta"
      ],
      0,
      0
   ],
   "nap":[
      [
         "naples",
         "napoli"
      ],
      3047,
      706
   ],
   "reb":[
      [
         "rebels"
      ],
      0,
      0
   ],
   "pry":[
      [
         "port royal"
      ],
      0,
      0
   ],
   "bru":[
      [
         "brunswick"
      ],
      2957,
      487
   ],
   "sie":[
      [
         "siena",
         "sienna"
      ],
      2985,
      672
   ],
   "cxi":[
      [
         "xi"
      ],
      0,
      0
   ],
   "wls":[
      [
         "wales"
      ],
      0,
      0
   ],
   "klm":[
      [
         "kalmyk"
      ],
      0,
      0
   ],
   "hur":[
      [
         "huron"
      ],
      0,
      0
   ],
   "yzd":[
      [
         "yazd"
      ],
      0,
      0
   ],
   "peg":[
      [
         "pegu"
      ],
      0,
      0
   ],
   "ire":[
      [
         "ireland"
      ],
      0,
      0
   ],
   "tau":[
      [
         "taungu"
      ],
      0,
      0
   ],
   "kon":[
      [
         "kongo"
      ],
      3032,
      1507
   ],
   "bpi":[
      [
         "biapas"
      ],
      0,
      0
   ],
   "xal":[
      [
         "xalisco"
      ],
      0,
      0
   ],
   "nub":[
      [
         "funj"
      ],
      0,
      0
   ],
   "ntz":[
      [
         "natchez"
      ],
      0,
      0
   ],
   "tab":[
      [
         "mazandaran"
      ],
      0,
      0
   ],
   "csu":[
      [
         "cusco"
      ],
      1671,
      1381
   ],
   "qng":[
      [
         "china",
         "qing"
      ],
      4581,
      971
   ],
   "kaq":[
      [
         "kaqchikel"
      ],
      0,
      0
   ],
   "kkc":[
      [
         "kikuchi"
      ],
      0,
      0
   ],
   "jlv":[
      [
         "jhalavad"
      ],
      0,
      0
   ],
   "peu":[
      [
         "peru"
      ],
      1633,
      1365
   ],
   "hat":[
      [
         "haiti"
      ],
      1695,
      899
   ],
   "bnj":[
      [
         "banjar"
      ],
      0,
      0
   ],
   "tar":[
      [
         "tarascan"
      ],
      0,
      0
   ],
   "brr":[
      [
         "berar"
      ],
      0,
      0
   ],
   "jml":[
      [
         "jumla"
      ],
      0,
      0
   ],
   "yok":[
      [
         "yokotan"
      ],
      0,
      0
   ],
   "tah":[
      [
         "tahontaenrat"
      ],
      0,
      0
   ],
   "cas":[
      [
         "castile",
         "castille"
      ],
      2743,
      707
   ],
   "azt":[
      [
         "aztec",
         "aztecs"
      ],
      1259,
      860
   ],
   "aus":[
      [
         "australia"
      ],
      4913,
      1711
   ],
   "dei":[
      [
         "dutch_east_indies"
      ],
      4438,
      1466
   ],
   "pue":[
      [
         "pueblo"
      ],
      1155,
      570
   ],
   "rup":[
      [
         "ruppin"
      ],
      0,
      0
   ],
   "sis":[
      [
         "sistan"
      ],
      0,
      0
   ],
   "jim":[
      [
         "jima"
      ],
      0,
      0
   ],
   "sty":[
      [
         "styria"
      ],
      3024,
      594
   ],
   "vit":[
      [
         "viti"
      ],
      0,
      0
   ],
   "mje":[
      [
         "majeerteen"
      ],
      0,
      0
   ],
   "lor":[
      [
         "lorraine"
      ],
      2905,
      555
   ],
   "kul":[
      [
         "kulin"
      ],
      0,
      0
   ],
   "war":[
      [
         "warsangali"
      ],
      0,
      0
   ],
   "tet":[
      [
         "tetouan"
      ],
      0,
      0
   ],
   "fkn":[
      [
         "franconia"
      ],
      0,
      0
   ],
   "tyo":[
      [
         "tyo"
      ],
      0,
      0
   ],
   "nss":[
      [
         "new_providence"
      ],
      0,
      0
   ],
   "ast":[
      [
         "astrakhan"
      ],
      0,
      0
   ],
   "nov":[
      [
         "novgorod"
      ],
      3320,
      347
   ],
   "xiu":[
      [
         "xiu"
      ],
      0,
      0
   ],
   "smb":[
      [
         "sambas"
      ],
      0,
      0
   ],
   "dmk":[
      [
         "demak"
      ],
      0,
      0
   ],
   "ubv":[
      [
         "munich",
         "m\u00c3\u00bcnchen"
      ],
      2986,
      573
   ],
   "dng":[
      [
         "dang"
      ],
      0,
      0
   ],
   "kni":[
      [
         "the_knights",
         "knights"
      ],
      3241,
      794
   ],
   "tun":[
      [
         "tunis"
      ],
      2937,
      802
   ],
   "per":[
      [
         "persia"
      ],
      3572,
      811
   ],
   "tiw":[
      [
         "tiwi"
      ],
      0,
      0
   ],
   "hmi":[
      [
         "kara_del",
         "kara"
      ],
      0,
      0
   ],
   "nav":[
      [
         "navarra"
      ],
      2783,
      676
   ],
   "pcj":[
      [
         "pacajes"
      ],
      0,
      0
   ],
   "mae":[
      [
         "maeda"
      ],
      0,
      0
   ],
   "wal":[
      [
         "wallachia"
      ],
      3209,
      635
   ],
   "ksk":[
      [
         "kaskaskia"
      ],
      0,
      0
   ],
   "blo":[
      [
         "beloozero"
      ],
      0,
      0
   ],
   "bel":[
      [
         "belgium"
      ],
      2885,
      519
   ],
   "mni":[
      [
         "mongnai"
      ],
      0,
      0
   ],
   "sus":[
      [
         "susquehannock"
      ],
      0,
      0
   ],
   "ker":[
      [
         "keres"
      ],
      0,
      0
   ],
   "atj":[
      [
         "aceh"
      ],
      0,
      0
   ],
   "nev":[
      [
         "nevers"
      ],
      0,
      0
   ],
   "npl":[
      [
         "nepal"
      ],
      0,
      0
   ],
   "mis":[
      [
         "miskito"
      ],
      0,
      0
   ],
   "bug":[
      [
         "buganda"
      ],
      0,
      0
   ],
   "yol":[
      [
         "yolngu"
      ],
      0,
      0
   ],
   "bhu":[
      [
         "bhutan"
      ],
      0,
      0
   ],
   "kac":[
      [
         "kachar"
      ],
      0,
      0
   ],
   "leb":[
      [
         "lebanon"
      ],
      0,
      0
   ],
   "brz":[
      [
         "brazil"
      ],
      2020,
      1360
   ],
   "sru":[
      [
         "saruhan"
      ],
      0,
      0
   ],
   "ktb":[
      [
         "kitabatake"
      ],
      0,
      0
   ],
   "kbu":[
      [
         "kaabu"
      ],
      0,
      0
   ],
   "cha":[
      [
         "champa"
      ],
      0,
      0
   ],
   "kbo":[
      [
         "kanem_bornu",
         "kanem"
      ],
      0,
      0
   ],
   "msc":[
      [
         "mescalero"
      ],
      0,
      0
   ],
   "swa":[
      [
         "swabia"
      ],
      0,
      0
   ],
   "snd":[
      [
         "sind"
      ],
      0,
      0
   ],
   "cht":[
      [
         "chorti"
      ],
      0,
      0
   ],
   "lou":[
      [
         "louisiana"
      ],
      0,
      0
   ],
   "srm":[
      [
         "sirmur"
      ],
      0,
      0
   ],
   "kal":[
      [
         "kale"
      ],
      0,
      0
   ],
   "ind":[
      [
         "indrapura"
      ],
      0,
      0
   ],
   "yat":[
      [
         "yatenga"
      ],
      0,
      0
   ],
   "ykt":[
      [
         "yokuts"
      ],
      0,
      0
   ],
   "lwa":[
      [
         "limbuwan"
      ],
      0,
      0
   ],
   "ash":[
      [
         "ashanti"
      ],
      0,
      0
   ],
   "est":[
      [
         "estonia"
      ],
      0,
      0
   ],
   "lap":[
      [
         "la_plata"
      ],
      0,
      0
   ],
   "klp":[
      [
         "kalpi"
      ],
      0,
      0
   ],
   "utr":[
      [
         "utrecht"
      ],
      0,
      0
   ],
   "sav":[
      [
         "savoy"
      ],
      2909,
      620
   ],
   "usa":[
      [
         "United States",
         "america",
         "murica",
         "u.s.a"
      ],
      1450,
      591
   ],
   "chl":[
      [
         "chile"
      ],
      1688,
      1791
   ],
   "bei":[
      [
         "brunei"
      ],
      4574,
      1355
   ],
   "tlg":[
      [
         "telingana"
      ],
      0,
      0
   ],
   "reg":[
      [
         "regensburg"
      ],
      0,
      0
   ],
   "moh":[
      [
         "mohawk"
      ],
      0,
      0
   ],
   "nzh":[
      [
         "nizhny"
      ],
      3457,
      391
   ],
   "tor":[
      [
         "tortuga"
      ],
      0,
      0
   ],
   "prg":[
      [
         "paraguay"
      ],
      0,
      0
   ],
   "sun":[
      [
         "sunda"
      ],
      0,
      0
   ],
   "wuu":[
      [
         "wu"
      ],
      0,
      0
   ],
   "gre":[
      [
         "greece"
      ],
      0,
      0
   ],
   "uts":[
      [
         "u-tsang",
         "tsang"
      ],
      4220,
      879
   ],
   "ord":[
      [
         "ormond"
      ],
      0,
      0
   ],
   "ttt":[
      [
         "tetaitokerau"
      ],
      0,
      0
   ],
   "vnz":[
      [
         "venezuela"
      ],
      1803,
      1083
   ],
   "tmb":[
      [
         "timbuktu"
      ],
      0,
      0
   ],
   "tim":[
      [
         "timurids",
         "timi",
         "timmy",
         "timy",
         "timmi"
      ],
      3753,
      851
   ],
   "mlk":[
      [
         "kharabakh"
      ],
      0,
      0
   ],
   "mbl":[
      [
         "bishnupur"
      ],
      0,
      0
   ],
   "jan":[
      [
         "jangladesh"
      ],
      0,
      0
   ],
   "nog":[
      [
         "nogai"
      ],
      3684,
      565
   ],
   "fly":[
      [
         "offaly"
      ],
      2691,
      454
   ],
   "spi":[
      [
         "sardiniapiedmont"
      ],
      0,
      0
   ],
   "bda":[
      [
         "baroda"
      ],
      0,
      0
   ],
   "ich":[
      [
         "ichisi"
      ],
      0,
      0
   ],
   "ntc":[
      [
         "natchitoches"
      ],
      0,
      0
   ],
   "lva":[
      [
         "livonia"
      ],
      0,
      0
   ],
   "kle":[
      [
         "cleves"
      ],
      0,
      0
   ],
   "tnj":[
      [
         "tanjore"
      ],
      0,
      0
   ],
   "rot":[
      [
         "rothenburg"
      ],
      0,
      0
   ],
   "kha":[
      [
         "mongolia"
      ],
      4568,
      601
   ],
   "frm":[
      [
         "formosa"
      ],
      0,
      0
   ],
   "bul":[
      [
         "bulgaria"
      ],
      3197,
      682
   ],
   "fla":[
      [
         "flanders"
      ],
      2857,
      508
   ],
   "kzh":[
      [
         "kazakh"
      ],
      0,
      0
   ],
   "kld":[
      [
         "kalundwe"
      ],
      0,
      0
   ],
   "dan":[
      [
         "denmark"
      ],
      2952,
      400
   ],
   "pro":[
      [
         "provence"
      ],
      2900,
      653
   ],
   "oyo":[
      [
         "oyo"
      ],
      0,
      0
   ],
   "jmb":[
      [
         "jambi"
      ],
      0,
      0
   ],
   "ada":[
      [
         "adal"
      ],
      3470,
      1247
   ],
   "idr":[
      [
         "idar"
      ],
      0,
      0
   ],
   "sbp":[
      [
         "sambalpur"
      ],
      0,
      0
   ],
   "mng":[
      [
         "ming"
      ],
      4581,
      971
   ],
   "bti":[
      [
         "semien"
      ],
      0,
      0
   ],
   "jsl":[
      [
         "jaisalmer"
      ],
      0,
      0
   ],
   "mfa":[
      [
         "montferrat"
      ],
      0,
      0
   ],
   "cal":[
      [
         "california"
      ],
      0,
      0
   ],
   "mlw":[
      [
         "malwa"
      ],
      4020,
      1024
   ],
   "msy":[
      [
         "mushasha"
      ],
      0,
      0
   ],
   "ard":[
      [
         "ardalan"
      ],
      0,
      0
   ],
   "pot":[
      [
         "potawatomi"
      ],
      0,
      0
   ],
   "glh":[
      [
         "golden_horde"
      ],
      0,
      0
   ],
   "kio":[
      [
         "kiowa"
      ],
      0,
      0
   ],
   "eri":[
      [
         "erie"
      ],
      0,
      0
   ],
   "pat":[
      [
         "pattani"
      ],
      0,
      0
   ],
   "kas":[
      [
         "yarkand"
      ],
      4050,
      768
   ],
   "mkp":[
      [
         "makwanpur"
      ],
      0,
      0
   ],
   "lun":[
      [
         "l\u00c3\u00bcneburg"
      ],
      0,
      0
   ],
   "pss":[
      [
         "passau"
      ],
      0,
      0
   ],
   "ans":[
      [
         "ansbach"
      ],
      2968,
      544
   ],
   "zaz":[
      [
         "zaporozhie"
      ],
      0,
      0
   ],
   "tlx":[
      [
         "tlaxcala"
      ],
      0,
      0
   ],
   "pal":[
      [
         "the_palatinate",
         "palatinate"
      ],
      2930,
      541
   ],
   "szo":[
      [
         "saluzzo"
      ],
      0,
      0
   ],
   "brb":[
      [
         "brabant"
      ],
      2878,
      507
   ],
   "ngp":[
      [
         "jharkhand"
      ],
      0,
      0
   ],
   "chy":[
      [
         "cheyenne"
      ],
      0,
      0
   ],
   "cba":[
      [
         "chiba"
      ],
      0,
      0
   ],
   "lai":[
      [
         "lau"
      ],
      0,
      0
   ],
   "lxa":[
      [
         "lan_xang"
      ],
      0,
      0
   ],
   "jnp":[
      [
         "jaunpur"
      ],
      4090,
      971
   ],
   "ktu":[
      [
         "kathmandu",
         "katmandu"
      ],
      4139,
      941
   ],
   "nko":[
      [
         "nkore"
      ],
      0,
      0
   ],
   "pha":[
      [
         "phagmodrupa"
      ],
      0,
      0
   ],
   "rwa":[
      [
         "rwanda"
      ],
      0,
      0
   ],
   "tki":[
      [
         "toki"
      ],
      0,
      0
   ],
   "hlr":[
      [
         "holy_roman_empire"
      ],
      3031,
      586
   ],
   "gnv":[
      [
         "geneva"
      ],
      0,
      0
   ],
   "air":[
      [
         "air"
      ],
      0,
      0
   ],
   "ayd":[
      [
         "aydin"
      ],
      0,
      0
   ],
   "tus":[
      [
         "tuscany"
      ],
      0,
      0
   ],
   "ubh":[
      [
         "buha"
      ],
      0,
      0
   ],
   "suk":[
      [
         "sukhothai"
      ],
      0,
      0
   ],
   "klk":[
      [
         "khalkha"
      ],
      0,
      0
   ],
   "pru":[
      [
         "prussia"
      ],
      3057,
      466
   ],
   "vrm":[
      [
         "vermont"
      ],
      0,
      0
   ],
   "msg":[
      [
         "mississage"
      ],
      0,
      0
   ],
   "sme":[
      [
         "samtskhe"
      ],
      0,
      0
   ],
   "mor":[
      [
         "morocco",
         "morroco",
         "marocco"
      ],
      2718,
      844
   ],
   "wru":[
      [
         "wurundjeri"
      ],
      0,
      0
   ],
   "tex":[
      [
         "texas"
      ],
      0,
      0
   ],
   "nat":[
      [
         "natives"
      ],
      0,
      0
   ],
   "bny":[
      [
         "bunyoro"
      ],
      0,
      0
   ],
   "chv":[
      [
         "chavchuveny"
      ],
      0,
      0
   ],
   "pow":[
      [
         "powhatan"
      ],
      0,
      0
   ],
   "asu":[
      [
         "asturias"
      ],
      0,
      0
   ],
   "kmn":[
      [
         "kumaon"
      ],
      0,
      0
   ],
   "adu":[
      [
         "andalusia"
      ],
      0,
      0
   ],
   "wly":[
      [
         "welayta"
      ],
      0,
      0
   ],
   "cnn":[
      [
         "clanricarde"
      ],
      0,
      0
   ],
   "zun":[
      [
         "zunghar"
      ],
      0,
      0
   ],
   "crt":[
      [
         "crete"
      ],
      0,
      0
   ],
   "ghr":[
      [
         "garhwal"
      ],
      0,
      0
   ],
   "myr":[
      [
         "yeren"
      ],
      0,
      0
   ],
   "lip":[
      [
         "lipan"
      ],
      0,
      0
   ],
   "vnl":[
      [
         "vanua levu"
      ],
      0,
      0
   ],
   "mak":[
      [
         "makuria"
      ],
      0,
      0
   ],
   "mku":[
      [
         "makua"
      ],
      0,
      0
   ],
   "bli":[
      [
         "bali"
      ],
      0,
      0
   ],
   "orm":[
      [
         "hormuz"
      ],
      3678,
      995
   ],
   "epi":[
      [
         "epirus"
      ],
      0,
      0
   ],
   "jfn":[
      [
         "jaffna"
      ],
      0,
      0
   ],
   "#hah":[
      [
         "hashshashin"
      ],
      0,
      0
   ],
   "abi":[
      [
         "abihka"
      ],
      0,
      0
   ],
   "mos":[
      [
         "muscovy"
      ],
      3380,
      415
   ],
   "zzz":[
      [
         "zazzau"
      ],
      0,
      0
   ],
   "mun":[
      [
         "munster"
      ],
      0,
      0
   ],
   "rug":[
      [
         "rugen"
      ],
      0,
      0
   ],
   "tea":[
      [
         "tearawa"
      ],
      0,
      0
   ],
   "ott":[
      [
         "ottawa"
      ],
      0,
      0
   ],
   "bej":[
      [
         "beja"
      ],
      0,
      0
   ],
   "jmn":[
      [
         "jan mayen"
      ],
      0,
      0
   ],
   "teu":[
      [
         "teutonic_order",
         "teutons",
         "teuton",
         "teutonic",
         "pruthenia"
      ],
      3121,
      453
   ],
   "bam":[
      [
         "bamberg"
      ],
      0,
      0
   ],
   "cob":[
      [
         "coburg"
      ],
      0,
      0
   ],
   "lib":[
      [
         "libertatia"
      ],
      0,
      0
   ],
   "ejz":[
      [
         "eastjianzhou"
      ],
      0,
      0
   ],
   "hsk":[
      [
         "hosokawa"
      ],
      4880,
      821
   ],
   "fad":[
      [
         "fadl"
      ],
      0,
      0
   ],
   "#tem":[
      [
         "knightstemplar"
      ],
      0,
      0
   ],
   "krl":[
      [
         "karelia"
      ],
      0,
      0
   ],
   "pgs":[
      [
         "pangasinan"
      ],
      0,
      0
   ],
   "dtt":[
      [
         "dithmarschen",
         "dirtsmarchen"
      ],
      2953,
      442
   ],
   "yem":[
      [
         "yemen"
      ],
      0,
      0
   ],
   "njr":[
      [
         "najran"
      ],
      0,
      0
   ],
   "chp":[
      [
         "champagne"
      ],
      0,
      0
   ],
   "tpa":[
      [
         "tupinamba"
      ],
      0,
      0
   ],
   "kic":[
      [
         "kiche"
      ],
      0,
      0
   ],
   "alt":[
      [
         "altamaha"
      ],
      0,
      0
   ],
   "mch":[
      [
         "manchu"
      ],
      0,
      0
   ],
   "cep":[
      [
         "corfu"
      ],
      0,
      0
   ],
   "gle":[
      [
         "geledi"
      ],
      0,
      0
   ],
   "mph":[
      [
         "muan phuang"
      ],
      0,
      0
   ],
   "mar":[
      [
         "marathas"
      ],
      0,
      0
   ],
   "feo":[
      [
         "theodoro"
      ],
      3334,
      635
   ],
   "brs":[
      [
         "barus"
      ],
      0,
      0
   ],
   "alb":[
      [
         "albania"
      ],
      3122,
      686
   ],
   "nax":[
      [
         "naxos"
      ],
      3185,
      768
   ],
   "ann":[
      [
         "annam"
      ],
      0,
      0
   ],
   "kzb":[
      [
         "kazembe"
      ],
      0,
      0
   ],
   "yar":[
      [
         "yaroslavl"
      ],
      0,
      0
   ],
   "sam":[
      [
         "samoa"
      ],
      0,
      0
   ],
   "gdw":[
      [
         "gondwana"
      ],
      0,
      0
   ],
   "ras":[
      [
         "rassids"
      ],
      3497,
      1143
   ],
   "mab":[
      [
         "malabar"
      ],
      0,
      0
   ],
   "tbr":[
      [
         "tabriz"
      ],
      0,
      0
   ],
   "pun":[
      [
         "punjab"
      ],
      0,
      0
   ],
   "sln":[
      [
         "sligo"
      ],
      0,
      0
   ],
   "buu":[
      [
         "burundi"
      ],
      0,
      0
   ],
   "wic":[
      [
         "wichita"
      ],
      0,
      0
   ],
   "byz":[
      [
         "byzantium"
      ],
      3243,
      700
   ],
   "shu":[
      [
         "shu"
      ],
      0,
      0
   ],
   "nor":[
      [
         "norway"
      ],
      2954,
      283
   ],
   "ctm":[
      [
         "chactemal"
      ],
      0,
      0
   ],
   "odh":[
      [
         "oudh"
      ],
      0,
      0
   ],
   "cnk":[
      [
         "chinook"
      ],
      0,
      0
   ],
   "prb":[
      [
         "porbandar"
      ],
      0,
      0
   ],
   "old":[
      [
         "oldenburg"
      ],
      0,
      0
   ],
   "maj":[
      [
         "majapahit"
      ],
      4543,
      1514
   ],
   "pen":[
      [
         "penobscot"
      ],
      0,
      0
   ],
   "ale":[
      [
         "alen\u00c3\u00a7on"
      ],
      0,
      0
   ],
   "fer":[
      [
         "ferrara"
      ],
      2992,
      636
   ],
   "btu":[
      [
         "butuan"
      ],
      0,
      0
   ],
   "mjz":[
      [
         "jianzhou"
      ],
      4837,
      651
   ],
   "kmt":[
      [
         "koch"
      ],
      0,
      0
   ],
   "jaj":[
      [
         "habsan"
      ],
      0,
      0
   ],
   "ask":[
      [
         "ashikaga"
      ],
      4929,
      816
   ],
   "bpr":[
      [
         "prome"
      ],
      0,
      0
   ],
   "vij":[
      [
         "vijayanagar",
         "Vijiyaangar",
         "viji"
      ],
      4038,
      1185
   ],
   "rzw":[
      [
         "butua"
      ],
      3251,
      1681
   ],
   "fez":[
      [
         "fez"
      ],
      0,
      0
   ],
   "zaf":[
      [
         "macina"
      ],
      0,
      0
   ],
   "chg":[
      [
         "chagatai"
      ],
      4190,
      661
   ],
   "qin":[
      [
         "qin"
      ],
      0,
      0
   ],
   "spl":[
      [
         "spoleto"
      ],
      0,
      0
   ],
   "coo":[
      [
         "coosa"
      ],
      0,
      0
   ],
   "teo":[
      [
         "teotitlan"
      ],
      0,
      0
   ],
   "hsa":[
      [
         "lübeck",
         "lubeck",
         "hansa"
      ],
      2972,
      448
   ],
   "mns":[
      [
         "thomond"
      ],
      0,
      0
   ],
   "cyp":[
      [
         "cyprus"
      ],
      0,
      0
   ],
   "csh":[
      [
         "shun"
      ],
      0,
      0
   ],
   "osa":[
      [
         "osage"
      ],
      0,
      0
   ],
   "mtr":[
      [
         "mataram"
      ],
      0,
      0
   ],
   "mge":[
      [
         "mongolempire"
      ],
      0,
      0
   ],
   "cnp":[
      [
         "can pech"
      ],
      0,
      0
   ],
   "sil":[
      [
         "silesia"
      ],
      0,
      0
   ],
   "bsh":[
      [
         "bashkiria"
      ],
      0,
      0
   ],
   "tio":[
      [
         "tionontate"
      ],
      0,
      0
   ],
   "pdv":[
      [
         "padova"
      ],
      0,
      0
   ],
   "rmn":[
      [
         "romania"
      ],
      0,
      0
   ],
   "shr":[
      [
         "sharjah"
      ],
      0,
      0
   ],
   "len":[
      [
         "lenape"
      ],
      0,
      0
   ],
   "tng":[
      [
         "tang"
      ],
      0,
      0
   ],
   "oji":[
      [
         "ojibwe"
      ],
      0,
      0
   ],
   "bne":[
      [
         "bone"
      ],
      0,
      0
   ],
   "ban":[
      [
         "banten"
      ],
      0,
      0
   ],
   "sca":[
      [
         "scandinavia"
      ],
      0,
      0
   ],
   "chu":[
      [
         "chukchi"
      ],
      0,
      0
   ],
   "sor":[
      [
         "sorbia"
      ],
      0,
      0
   ],
   "lit":[
      [
         "lithuania"
      ],
      3264,
      487
   ],
   "mul":[
      [
         "multan"
      ],
      0,
      0
   ],
   "dgl":[
      [
         "maldives"
      ],
      0,
      0
   ],
   "ful":[
      [
         "fulo"
      ],
      0,
      0
   ],
   "cof":[
      [
         "cofitachequi"
      ],
      0,
      0
   ],
   "alo":[
      [
         "alodia"
      ],
      0,
      0
   ],
   "jin":[
      [
         "jin"
      ],
      0,
      0
   ],
   "ice":[
      [
         "iceland"
      ],
      0,
      0
   ],
   "glg":[
      [
         "glogau"
      ],
      0,
      0
   ],
   "pom":[
      [
         "pomerania"
      ],
      0,
      0
   ],
   "hau":[
      [
         "hausa"
      ],
      0,
      0
   ],
   "cat":[
      [
         "catalonia"
      ],
      0,
      0
   ],
   "anu":[
      [
         "ainu"
      ],
      0,
      0
   ],
   "gaz":[
      [
         "gazikumukh"
      ],
      0,
      0
   ],
   "knz":[
      [
         "konstanz"
      ],
      0,
      0
   ],
   "mzb":[
      [
         "mzab"
      ],
      0,
      0
   ],
   "mai":[
      [
         "mainz"
      ],
      0,
      0
   ],
   "mhr":[
      [
         "mahra"
      ],
      0,
      0
   ],
   "mlh":[
      [
         "mulhouse"
      ],
      0,
      0
   ],
   "mls":[
      [
         "maliseet"
      ],
      0,
      0
   ],
   "hni":[
      [
         "hasinai"
      ],
      0,
      0
   ],
   "maz":[
      [
         "mazovia"
      ],
      0,
      0
   ],
   "tyr":[
      [
         "tyrone"
      ],
      0,
      0
   ],
   "brg":[
      [
         "berg"
      ],
      0,
      0
   ],
   "ksj":[
      [
         "kasanje"
      ],
      0,
      0
   ],
   "cca":[
      [
         "chisca"
      ],
      0,
      0
   ],
   "qui":[
      [
         "quizquiz"
      ],
      0,
      0
   ],
   "kan":[
      [
         "kano"
      ],
      0,
      0
   ],
   "ass":[
      [
         "assam"
      ],
      0,
      0
   ],
   "ndo":[
      [
         "ndongo"
      ],
      0,
      0
   ],
   "peq":[
      [
         "pequot"
      ],
      0,
      0
   ],
   "ksp":[
      [
         "kispoko"
      ],
      0,
      0
   ],
   "mbz":[
      [
         "montfort-bregenz"
      ],
      0,
      0
   ],
   "lar":[
      [
         "larrakia"
      ],
      0,
      0
   ],
   "hdr":[
      [
         "hadramut"
      ],
      0,
      0
   ],
   "gen":[
      [
         "genoa"
      ],
      2944,
      636
   ],
   "plw":[
      [
         "palawa"
      ],
      0,
      0
   ],
   "mad":[
      [
         "madurai"
      ],
      0,
      0
   ],
   "klh":[
      [
         "kalahandi"
      ],
      0,
      0
   ],
   "trs":[
      [
         "transoxiana"
      ],
      3717,
      738
   ],
   "ulm":[
      [
         "ulm"
      ],
      2963,
      555
   ],
   "ccm":[
      [
         "chichimeca"
      ],
      0,
      0
   ],
   "joh":[
      [
         "johor"
      ],
      0,
      0
   ],
   "vil":[
      [
         "viti levu"
      ],
      0,
      0
   ],
   "tou":[
      [
         "toulouse"
      ],
      0,
      0
   ],
   "hrz":[
      [
         "herzegovina"
      ],
      0,
      0
   ],
   "tkd":[
      [
         "takeda"
      ],
      0,
      0
   ],
   "icm":[
      [
         "ichma"
      ],
      0,
      0
   ],
   "sst":[
      [
         "shan"
      ],
      0,
      0
   ],
   "rag":[
      [
         "ragusa"
      ],
      3090,
      672
   ],
   "ant":[
      [
         "antemoro"
      ],
      0,
      0
   ],
   "lng":[
      [
         "liang"
      ],
      0,
      0
   ],
   "pim":[
      [
         "pima"
      ],
      0,
      0
   ],
   "mlb":[
      [
         "manipur"
      ],
      0,
      0
   ],
   "cro":[
      [
         "croatia"
      ],
      0,
      0
   ],
   "wur":[
      [
         "wurttemberg"
      ],
      2947,
      557
   ],
   "ckw":[
      [
         "chokwe"
      ],
      0,
      0
   ],
   "sat":[
      [
         "satapo"
      ],
      0,
      0
   ],
   "srg":[
      [
         "surguja"
      ],
      0,
      0
   ],
   "pan":[
      [
         "panna"
      ],
      0,
      0
   ],
   "rum":[
      [
         "r\u00c3\u00bbm"
      ],
      0,
      0
   ],
   "bre":[
      [
         "bremen"
      ],
      0,
      0
   ],
   "iro":[
      [
         "iroquois"
      ],
      0,
      0
   ],
   "one":[
      [
         "oneida"
      ],
      0,
      0
   ],
   "sol":[
      [
         "solon"
      ],
      0,
      0
   ],
   "nup":[
      [
         "nupe"
      ],
      0,
      0
   ],
   "plc":[
      [
         "commonwealth"
      ],
      0,
      0
   ],
   "utn":[
      [
         "utsunomiya"
      ],
      0,
      0
   ],
   "slo":[
      [
         "nitra",
         "nitra/hungary"
      ],
      3100,
      551
   ],
   "maw":[
      [
         "marwar"
      ],
      0,
      0
   ],
   "joa":[
      [
         "joara"
      ],
      0,
      0
   ],
   "chc":[
      [
         "chu"
      ],
      0,
      0
   ],
   "plb":[
      [
         "palembang"
      ],
      4436,
      1448
   ],
   "dah":[
      [
         "dahomey"
      ],
      0,
      0
   ],
   "gwa":[
      [
         "gwalior"
      ],
      0,
      0
   ],
   "mli":[
      [
         "malindi"
      ],
      0,
      0
   ],
   "sic":[
      [
         "sicily",
         "two_scicilies"
      ],
      3031,
      769
   ],
   "aju":[
      [
         "ajuuraan"
      ],
      3514,
      1329
   ],
   "sof":[
      [
         "segu"
      ],
      0,
      0
   ],
   "sul":[
      [
         "sulu"
      ],
      0,
      0
   ],
   "mba":[
      [
         "mombasa"
      ],
      0,
      0
   ],
   "lac":[
      [
         "lacandon"
      ],
      0,
      0
   ],
   "mam":[
      [
         "mamluks"
      ],
      3286,
      909
   ],
   "kol":[
      [
         "cologne"
      ],
      2938,
      502
   ],
   "dar":[
      [
         "darfur"
      ],
      0,
      0
   ],
   "bgl":[
      [
         "bagelkhand"
      ],
      0,
      0
   ],
   "mhx":[
      [
         "haixi"
      ],
      0,
      0
   ],
   "sna":[
      [
         "sonora"
      ],
      0,
      0
   ],
   "cmi":[
      [
         "miao"
      ],
      0,
      0
   ],
   "arn":[
      [
         "arendaronon"
      ],
      0,
      0
   ],
   "cya":[
      [
         "chachapoya"
      ],
      0,
      0
   ],
   "pad":[
      [
         "paderborn"
      ],
      0,
      0
   ],
   "ptt":[
      [
         "patna"
      ],
      0,
      0
   ],
   "val":[
      [
         "valencia"
      ],
      0,
      0
   ],
   "boh":[
      [
         "bohemia"
      ],
      3033,
      529
   ],
   "ayu":[
      [
         "ayutthaya"
      ],
      4380,
      1167
   ],
   "kau":[
      [
         "kaurna"
      ],
      0,
      0
   ],
   "mug":[
      [
         "mughals"
      ],
      0,
      0
   ],
   "nag":[
      [
         "nagpur"
      ],
      0,
      0
   ],
   "nga":[
      [
         "nagaur"
      ],
      0,
      0
   ],
   "mex":[
      [
         "mexico"
      ],
      1212,
      845
   ],
   "aug":[
      [
         "augsburg"
      ],
      0,
      0
   ],
   "hin":[
      [
         "hindustan"
      ],
      0,
      0
   ],
   "krm":[
      [
         "kerman"
      ],
      0,
      0
   ],
   "rjp":[
      [
         "rajputana"
      ],
      0,
      0
   ],
   "kts":[
      [
         "katsina"
      ],
      0,
      0
   ],
   "nrm":[
      [
         "normandy"
      ],
      0,
      0
   ],
   "thu":[
      [
         "thuringia"
      ],
      0,
      0
   ],
   "clb":[
      [
         "calenberg"
      ],
      0,
      0
   ],
   "mik":[
      [
         "mikmaq"
      ],
      0,
      0
   ],
   "ues":[
      [
         "uesugi"
      ],
      4977,
      786
   ],
   "foi":[
      [
         "foix"
      ],
      0,
      0
   ],
   "abb":[
      [
         "dongola"
      ],
      0,
      0
   ],
   "ita":[
      [
         "italy"
      ],
      2972,
      637
   ],
   "etr":[
      [
         "etruria"
      ],
      0,
      0
   ],
   "sho":[
      [
         "shoshone"
      ],
      0,
      0
   ],
   "mei":[
      [
         "meissen"
      ],
      0,
      0
   ],
   "oma":[
      [
         "oman"
      ],
      3698,
      1033
   ],
   "pis":[
      [
         "pisa"
      ],
      0,
      0
   ],
   "msa":[
      [
         "malaya"
      ],
      0,
      0
   ],
   "efr":[
      [
         "east_frisia",
         "frisa"
      ],
      2923,
      463
   ],
   "sos":[
      [
         "sus"
      ],
      2659,
      916
   ],
   "bsg":[
      [
         "busoga"
      ],
      0,
      0
   ],
   "orl":[
      [
         "orleans"
      ],
      2831,
      579
   ],
   "ohk":[
      [
         "ohkay owingeh"
      ],
      0,
      0
   ],
   "anz":[
      [
         "anizah"
      ],
      0,
      0
   ],
   "cli":[
      [
         "cilli"
      ],
      0,
      0
   ],
   "vie":[
      [
         "vientiane"
      ],
      0,
      0
   ],
   "sia":[
      [
         "siam"
      ],
      4388,
      1153
   ],
   "mon":[
      [
         "montenegro"
      ],
      0,
      0
   ],
   "lbv":[
      [
         "landshut"
      ],
      2997,
      557
   ],
   "kok":[
      [
         "ferghana"
      ],
      0,
      0
   ],
   "neh":[
      [
         "nehiyaw"
      ],
      0,
      0
   ],
   "oda":[
      [
         "oda"
      ],
      4944,
      814
   ],
   "mah":[
      [
         "mahican"
      ],
      0,
      0
   ],
   "tua":[
      [
         "tapuia"
      ],
      0,
      0
   ],
   "alh":[
      [
         "haasa"
      ],
      0,
      0
   ],
   "srv":[
      [
         "shirvan"
      ],
      3565,
      712
   ],
   "chh":[
      [
         "chahar"
      ],
      0,
      0
   ],
   "ito":[
      [
         "ito"
      ],
      0,
      0
   ],
   "kut":[
      [
         "kutai"
      ],
      0,
      0
   ],
   "yua":[
      [
         "yuan"
      ],
      0,
      0
   ],
   "hsc":[
      [
         "gaeldom"
      ],
      0,
      0
   ],
   "zni":[
      [
         "zuni"
      ],
      0,
      0
   ],
   "ven":[
      [
         "venice"
      ],
      2999,
      606
   ],
   "num":[
      [
         "nuremberg"
      ],
      0,
      0
   ],
   "bur":[
      [
         "burgundy"
      ],
      2887,
      587
   ],
   "osh":[
      [
         "osheaga"
      ],
      0,
      0
   ],
   "kub":[
      [
         "kuba"
      ],
      0,
      0
   ],
   "ynu":[
      [
         "yanuwa"
      ],
      0,
      0
   ],
   "zim":[
      [
         "mutapa"
      ],
      0,
      0
   ],
   "kho":[
      [
         "khorasan"
      ],
      0,
      0
   ],
   "crn":[
      [
         "cornwall"
      ],
      0,
      0
   ],
   "mir":[
      [
         "imerina"
      ],
      0,
      0
   ],
   "mrk":[
      [
         "marrakesh"
      ],
      0,
      0
   ],
   "ouc":[
      [
         "ouchi"
      ],
      0,
      0
   ],
   "kor":[
      [
         "korea"
      ],
      4782,
      748
   ],
   "gel":[
      [
         "gelre"
      ],
      2900,
      487
   ],
   "khi":[
      [
         "khiva"
      ],
      0,
      0
   ],
   "hua":[
      [
         "huai"
      ],
      0,
      0
   ],
   "coc":[
      [
         "cocomes"
      ],
      0,
      0
   ],
   "bga":[
      [
         "baglana"
      ],
      0,
      0
   ],
   "alg":[
      [
         "algiers"
      ],
      0,
      0
   ],
   "koi":[
      [
         "mann"
      ],
      0,
      0
   ],
   "daw":[
      [
         "dawasir"
      ],
      0,
      0
   ],
   "cre":[
      [
         "creek"
      ],
      0,
      0
   ],
   "soo":[
      [
         "so"
      ],
      0,
      0
   ],
   "por":[
      [
         "portugal"
      ],
      2680,
      723
   ],
   "mer":[
      [
         "merina_kingdom",
         "merina"
      ],
      3541,
      1710
   ],
   "me2":[
      [
         "mewar"
      ],
      3948,
      982
   ],
   "ked":[
      [
         "kedah"
      ],
      0,
      0
   ],
   "sle":[
      [
         "sale"
      ],
      0,
      0
   ],
   "mlo":[
      [
         "milan", "lombardy"
      ],
      2944,
      619
   ],
   "mys":[
      [
         "mysore"
      ],
      4004,
      1202
   ],
   "hda":[
      [
         "haida"
      ],
      0,
      0
   ],
   "wam":[
      [
         "wampanoag"
      ],
      0,
      0
   ],
   "atw":[
      [
         "attiwandaron"
      ],
      0,
      0
   ],
   "ram":[
      [
         "ramazan"
      ],
      0,
      0
   ],
   "mcm":[
      [
         "ire_munster"
      ],
      2665,
      488
   ],
   "moe":[
      [
         "morea"
      ],
      0,
      0
   ],
   "eng":[
      [
         "england",
         "britain",
         "gb",
         "uk"
      ],
      2793,
      478
   ],
   "asa":[
      [
         "asakura"
      ],
      0,
      0
   ],
   "maa":[
      [
         "mataatua"
      ],
      0,
      0
   ],
   "ned":[
      [
         "netherlands"
      ],
      2877,
      491
   ],
   "nzl":[
      [
         "zealandia"
      ],
      0,
      0
   ],
   "mna":[
      [
         "maynila"
      ],
      0,
      0
   ],
   "ach":[
      [
         "achaea"
      ],
      0,
      0
   ],
   "ahm":[
      [
         "ahmednagar"
      ],
      0,
      0
   ],
   "mva":[
      [
         "moravia"
      ],
      0,
      0
   ],
   "lig":[
      [
         "ligor"
      ],
      0,
      0
   ],
   "kel":[
      [
         "kelantan"
      ],
      0,
      0
   ],
   "bng":[
      [
         "bengal"
      ],
      4193,
      994
   ],
   "btn":[
      [
         "buton"
      ],
      0,
      0
   ],
   "ori":[
      [
         "orissa"
      ],
      4153,
      1056
   ],
   "trt":[
      [
         "tirhut"
      ],
      0,
      0
   ],
   "koj":[
      [
         "jerusalem"
      ],
      0,
      0
   ],
   "ptg":[
      [
         "potiguara"
      ],
      0,
      0
   ],
   "goc":[
      [
         "golkonda"
      ],
      0,
      0
   ],
   "tog":[
      [
         "tonga"
      ],
      0,
      0
   ],
   "hjo":[
      [
         "hojo"
      ],
      0,
      0
   ],
   "tpq":[
      [
         "tupiniquim"
      ],
      0,
      0
   ],
   "afg":[
      [
         "afghanistan"
      ],
      3883,
      836
   ],
   "plt":[
      [
         "polotsk"
      ],
      0,
      0
   ],
   "lna":[
      [
         "lan_na"
      ],
      0,
      0
   ],
   "ger":[
      [
         "germany"
      ],
      3010,
      476
   ],
   "fra":[
      [
         "france",
         "fr",
         "bigblueblob",
         "baguette"
      ],
      2861,
      562
   ],
   "rtt":[
      [
         "ratanpur"
      ],
      0,
      0
   ],
   "ksh":[
      [
         "kashmir"
      ],
      0,
      0
   ],
   "srh":[
      [
         "sirhind"
      ],
      3959,
      885
   ],
   "mia":[
      [
         "mianjin"
      ],
      0,
      0
   ],
   "mat":[
      [
         "matlatzinca"
      ],
      0,
      0
   ],
   "bos":[
      [
         "bosnia"
      ],
      3100,
      650
   ],
   "may":[
      [
         "maya"
      ],
      0,
      0
   ],
   "cra":[
      [
         "charca"
      ],
      0,
      0
   ],
   "jar":[
      [
         "jarai"
      ],
      0,
      0
   ],
   "syr":[
      [
         "syria"
      ],
      3376,
      813
   ],
   "klt":[
      [
         "kolathunad"
      ],
      0,
      0
   ],
   "lie":[
      [
         "liege"
      ],
      0,
      0
   ],
   "hst":[
      [
         "huastec"
      ],
      0,
      0
   ],
   "tdo":[
      [
         "tondo"
      ],
      0,
      0
   ],
   "uhw":[
      [
         "hawaiiunited"
      ],
      0,
      0
   ],
   "sar":[
      [
         "sardinia",
         "piedmont",
         "sardinia-piedmont",
         "spi"
      ],
      2949,
      720
   ],
   "mkl":[
      [
         "mecklenburg"
      ],
      0,
      0
   ],
   "swe":[
      [
         "sweden"
      ],
      3040,
      300
   ],
   "yao":[
      [
         "yao"
      ],
      0,
      0
   ],
   "gal":[
      [
         "galicia"
      ],
      0,
      0
   ],
   "lot":[
      [
         "lotharingia"
      ],
      2846,
      523
   ],
   "jji":[
      [
         "janjiro"
      ],
      0,
      0
   ],
   "chm":[
      [
         "chimu"
      ],
      0,
      0
   ],
   "ryu":[
      [
         "ryukyu"
      ],
      0,
      0
   ],
   "cgs":[
      [
         "changsheng"
      ],
      0,
      0
   ],
   "osn":[
      [
         "osnabruck"
      ],
      0,
      0
   ],
   "ono":[
      [
         "onondaga"
      ],
      0,
      0
   ],
   "agq":[
      [
         "algonquin"
      ],
      0,
      0
   ],
   "par":[
      [
         "parma"
      ],
      0,
      0
   ],
   "psa":[
      [
         "pasai"
      ],
      0,
      0
   ],
   "guj":[
      [
         "gujarat"
      ],
      3941,
      1029
   ],
   "eor":[
      [
         "eora"
      ],
      0,
      0
   ],
   "grj":[
      [
         "garjat"
      ],
      0,
      0
   ],
   "qas":[
      [
         "qasim"
      ],
      0,
      0
   ],
   "yue":[
      [
         "yue"
      ],
      0,
      0
   ],
   "gug":[
      [
         "guge"
      ],
      0,
      0
   ],
   "#jom":[
      [
         "jomsvikings"
      ],
      0,
      0
   ],
   "cam":[
      [
         "united_central_america"
      ],
      0,
      0
   ],
   "mjo":[
      [
         "majorca"
      ],
      0,
      0
   ],
   "gmi":[
      [
         "gamilaraay"
      ],
      0,
      0
   ],
   "ime":[
      [
         "imereti"
      ],
      3472,
      682
   ],
   "pap":[
      [
         "papal_states",
         "pope",
         "papal_state",
         "papal"
      ],
      3002,
      673
   ],
   "sal":[
      [
         "salish"
      ],
      0,
      0
   ],
   "mka":[
      [
         "mongkawng"
      ],
      0,
      0
   ],
   "arb":[
      [
         "arabia"
      ],
      0,
      0
   ],
   "luw":[
      [
         "luwu"
      ],
      0,
      0
   ],
   "shl":[
      [
         "holstein"
      ],
      2948,
      426
   ],
   "gra":[
      [
         "granada"
      ],
      2755,
      773
   ],
   "dli":[
      [
         "deli"
      ],
      0,
      0
   ],
   "hwk":[
      [
         "hathawekela"
      ],
      0,
      0
   ],
   "hes":[
      [
         "hesse",
         "hessen"
      ],
      2943,
      513
   ],
   "cab":[
      [
         "carib"
      ],
      1829,
      1036
   ],
   "wol":[
      [
         "wolgast"
      ],
      3070,
      442
   ],
   "kat":[
      [
         "kathiawar"
      ],
      0,
      0
   ],
   "jol":[
      [
         "jolof"
      ],
      0,
      0
   ],
   "tan":[
      [
         "tainui"
      ],
      0,
      0
   ],
   "cey":[
      [
         "ceylon"
      ],
      0,
      0
   ],
   "sba":[
      [
         "shiba"
      ],
      4993,
      751
   ],
   "dal":[
      [
         "dalmatia"
      ],
      0,
      0
   ],
   "sax":[
      [
         "saxony"
      ],
      3003,
      509
   ],
   "ksi":[
      [
         "kasihta"
      ],
      0,
      0
   ],
   "ham":[
      [
         "hamburg"
      ],
      2957,
      452
   ],
   "tre":[
      [
         "trebizond"
      ],
      0,
      0
   ],
   "loa":[
      [
         "loango"
      ],
      0,
      0
   ],
   "cmp":[
      [
         "rewa_kantha"
      ],
      0,
      0
   ],
   "zan":[
      [
         "kilwa"
      ],
      3418,
      1548
   ],
   "tfl":[
      [
         "tafilalt"
      ],
      0,
      0
   ],
   "nak":[
      [
         "nakawe"
      ],
      0,
      0
   ],
   "ara":[
      [
         "aragon"
      ],
      2810,
      694
   ],
   "kry":[
      [
         "gilan"
      ],
      0,
      0
   ],
   "crb":[
      [
         "cirebon"
      ],
      0,
      0
   ],
   "amg":[
      [
         "armagnac"
      ],
      0,
      0
   ],
   "bts":[
      [
         "betsimisaraka"
      ],
      0,
      0
   ],
   "kaf":[
      [
         "kaffa"
      ],
      0,
      0
   ],
   "chi":[
      [
         "chickasaw"
      ],
      0,
      0
   ],
   "noo":[
      [
         "noongar"
      ],
      0,
      0
   ],
   "bsr":[
      [
         "basra"
      ],
      0,
      0
   ],
   "pir":[
      [
         "pirates"
      ],
      0,
      0
   ],
   "vnd":[
      [
         "venad"
      ],
      0,
      0
   ],
   "egy":[
      [
         "egypt"
      ],
      3296,
      905
   ],
   "fin":[
      [
         "finland"
      ],
      0,
      0
   ],
   "hai":[
      [
         "hainaut"
      ],
      0,
      0
   ],
   "hol":[
      [
         "holland",
         "dutch"
      ],
      2877,
      491
   ],
   "lux":[
      [
         "luxembourg"
      ],
      0,
      0
   ],
   "luc":[
      [
         "lucca"
      ],
      0,
      0
   ],
   "rfr":[
      [
         "nanbu"
      ],
      0,
      0
   ],
   "ptl":[
      [
         "palitana"
      ],
      0,
      0
   ],
   "paw":[
      [
         "pawnee"
      ],
      0,
      0
   ],
   "syg":[
      [
         "sarig_yogir"
      ],
      0,
      0
   ],
   "gbr":[
      [
         "great britain"
      ],
      0,
      0
   ],
   "mpc":[
      [
         "mapuche"
      ],
      0,
      0
   ],
   "arp":[
      [
         "arapaho"
      ],
      0,
      0
   ],
   "tlc":[
      [
         "tlemcen"
      ],
      2796,
      831
   ],
   "oto":[
      [
         "otomi"
      ],
      0,
      0
   ],
   "chd":[
      [
         "chanda"
      ],
      0,
      0
   ],
   "isk":[
      [
         "isshiki"
      ],
      0,
      0
   ],
   "avr":[
      [
         "avaria"
      ],
      0,
      0
   ],
   "sok":[
      [
         "sokoto"
      ],
      2942,
      1232
   ],
   "mol":[
      [
         "moldavia"
      ],
      3246,
      598
   ],
   "rmp":[
      [
         "rohilkhand"
      ],
      0,
      0
   ],
   "arm":[
      [
         "armenia"
      ],
      0,
      0
   ],
   "ccq":[
      [
         "calchaqui"
      ],
      0,
      0
   ],
   "shn":[
      [
         "shoni"
      ],
      0,
      0
   ],
   "vol":[
      [
         "galicia\u00e2\u20ac\u201cvolhynia"
      ],
      0,
      0
   ],
   "qar":[
      [
         "qara_qoyunlu",
         "qara"
      ],
      3501,
      807
   ],
   "wsi":[
      [
         "westindies"
      ],
      0,
      0
   ],
   "tur":[
      [
         "ottomans",
         "turks",
         "kebab",
         "ottos",
         "otos",
         "otomans",
         "ottoman",
         "otto",
         "ottoblob",
         "otoblob"
      ],
      3201,
      684
   ],
   "bav":[
      [
         "bavaria"
      ],
      0,
      0
   ],
   "tot":[
      [
         "totonac"
      ],
      0,
      0
   ],
   "ste":[
      [
         "stettin"
      ],
      0,
      0
   ],
   "kar":[
      [
         "karaman"
      ],
      3319,
      766
   ],
   "bra":[
      [
         "brandenburg",
         "bb"
      ],
      3010,
      476
   ],
   "cao":[
      [
         "cahokia"
      ],
      0,
      0
   ],
   "mod":[
      [
         "modena"
      ],
      0,
      0
   ],
   "bal":[
      [
         "baluchistan"
      ],
      0,
      0
   ],
   "coi":[
      [
         "coixtlahuaca"
      ],
      0,
      0
   ],
   "tgt":[
      [
         "touggourt"
      ],
      0,
      0
   ],
   "btl":[
      [
         "bitlis"
      ],
      0,
      0
   ],
   "hsn":[
      [
         "hisn kayfa"
      ],
      0,
      0
   ],
   "can":[
      [
         "canada"
      ],
      1130,
      229
   ],
   "rus":[
      [
         "russia",
         "udssr",
         "ussr",
         "soviet",
         "soviet_union",
         "soviets"
      ],
      3461,
      398
   ],
   "irq":[
      [
         "iraq"
      ],
      0,
      0
   ],
   "gam":[
      [
         "guamar"
      ],
      0,
      0
   ],
   "sha":[
      [
         "shawnee"
      ],
      0,
      0
   ],
   "mag":[
      [
         "magdeburg"
      ],
      0,
      0
   ],
   "yor":[
      [
         "andhra"
      ],
      0,
      0
   ],
   "blg":[
      [
         "bologna"
      ],
      0,
      0
   ],
   "aqu":[
      [
         "aquileia"
      ],
      0,
      0
   ],
   "inc":[
      [
         "inca"
      ],
      0,
      0
   ],
   "haw":[
      [
         "hawaii"
      ],
      0,
      0
   ],
   "itz":[
      [
         "itza"
      ],
      0,
      0
   ],
   "att":[
      [
         "attignawantan"
      ],
      0,
      0
   ],
   "anl":[
      [
         "anilco"
      ],
      0,
      0
   ],
   "cia":[
      [
         "chiaha"
      ],
      0,
      0
   ],
   "akk":[
      [
         "aq"
      ],
      3425,
      775
   ],
   "ath":[
      [
         "athens"
      ],
      3170,
      755
   ],
   "spa":[
      [
         "spain"
      ],
      2743,
      707
   ],
   "cdl":[
      [
         "dali"
      ],
      0,
      0
   ],
   "got":[
      [
         "gotland"
      ],
      0,
      0
   ],
   "dgb":[
      [
         "dagbon"
      ],
      0,
      0
   ],
   "sio":[
      [
         "sioux"
      ],
      0,
      0
   ],
   "csk":[
      [
         "chosokabe"
      ],
      0,
      0
   ],
   "mpa":[
      [
         "mongpai"
      ],
      0,
      0
   ],
   "tai":[
      [
         "tairona"
      ],
      0,
      0
   ],
   "ksd":[
      [
         "khoshuud"
      ],
      0,
      0
   ],
   "pah":[
      [
         "pahang"
      ],
      0,
      0
   ],
   "nhx":[
      [
         "northhaixi"
      ],
      0,
      0
   ],
   "auv":[
      [
         "auvergne"
      ],
      0,
      0
   ],
   "mgr":[
      [
         "maregheh"
      ],
      0,
      0
   ],
   "psk":[
      [
         "pskov"
      ],
      0,
      0
   ],
   "krc":[
      [
         "korchin"
      ],
      0,
      0
   ],
   "eth":[
      [
         "ethiopia"
      ],
      3396,
      1207
   ],
   "bar":[
      [
         "bar"
      ],
      0,
      0
   ],
   "mth":[
      [
         "meath"
      ],
      0,
      0
   ],
   "soa":[
      [
         "shewa"
      ],
      0,
      0
   ],
   "tib":[
      [
         "tibet"
      ],
      4221,
      900
   ],
   "dai":[
      [
         "dai_viet"
      ],
      4450,
      1053
   ],
   "fri":[
      [
         "friesland"
      ],
      2910,
      467
   ],
   "otm":[
      [
         "otomo"
      ],
      0,
      0
   ],
   "khd":[
      [
         "khandesh"
      ],
      0,
      0
   ],
   "rya":[
      [
         "ryazan"
      ],
      0,
      0
   ],
   "khm":[
      [
         "khmer"
      ],
      4460,
      1199
   ],
   "pch":[
      [
         "pacaha"
      ],
      0,
      0
   ],
   "sdy":[
      [
         "sadiya"
      ],
      0,
      0
   ],
   "ili":[
      [
         "illinois"
      ],
      0,
      0
   ],
   "fox":[
      [
         "fox"
      ],
      0,
      0
   ],
   "kid":[
      [
         "kildare"
      ],
      2696,
      465
   ],
   "rva":[
      [
         "ravensburg"
      ],
      0,
      0
   ],
   "pte":[
      [
         "pate"
      ],
      0,
      0
   ],
   "lua":[
      [
         "luang prabang"
      ],
      0,
      0
   ],
   "mfl":[
      [
         "mikhlaf"
      ],
      0,
      0
   ],
   "kra":[
      [
         "krakow"
      ],
      0,
      0
   ],
   "hob":[
      [
         "hobyo"
      ],
      0,
      0
   ],
   "mem":[
      [
         "memmingen"
      ],
      0,
      0
   ],
   "bha":[
      [
         "bharat"
      ],
      0,
      0
   ],
   "wcy":[
      [
         "wichiyena"
      ],
      0,
      0
   ],
   "tak":[
      [
         "takitimu"
      ],
      0,
      0
   ],
   "cho":[
      [
         "choctaw"
      ],
      0,
      0
   ],
   "har":[
      [
         "harar"
      ],
      0,
      0
   ],
   "ukr":[
      [
         "ruthenia"
      ],
      0,
      0
   ],
   "kur":[
      [
         "kurland"
      ],
      0,
      0
   ],
   "liv":[
      [
         "livonian_order",
         "livonian"
      ],
      3221,
      372
   ],
   "bij":[
      [
         "bijapur"
      ],
      0,
      0
   ],
   "men":[
      [
         "mentese"
      ],
      0,
      0
   ],
   "kjh":[
      [
         "keonhjar"
      ],
      0,
      0
   ],
   "nsa":[
      [
         "nassau"
      ],
      0,
      0
   ],
   "prm":[
      [
         "perm"
      ],
      3628,
      297
   ],
   "rha":[
      [
         "rhade"
      ],
      0,
      0
   ],
   "try":[
      [
         "tyrconnell"
      ],
      0,
      0
   ],
   "gol":[
      [
         "great_horde"
      ],
      3462,
      533
   ],
   "col":[
      [
         "colombia"
      ],
      0,
      0
   ],
   "ber":[
      [
         "berry"
      ],
      0,
      0
   ],
   "qto":[
      [
         "quito"
      ],
      0,
      0
   ],
   "kng":[
      [
         "kong"
      ],
      0,
      0
   ],
   "akt":[
      [
         "ando"
      ],
      0,
      0
   ],
   "cja":[
      [
         "cajamarca"
      ],
      0,
      0
   ],
   "mal":[
      [
         "mali"
      ],
      2664,
      1215
   ],
   "oir":[
      [
         "oirat"
      ],
      4350,
      621
   ],
   "knd":[
      [
         "kandy"
      ],
      0,
      0
   ],
   "inn":[
      [
         "innu"
      ],
      0,
      0
   ],
   "naj":[
      [
         "najd"
      ],
      0,
      0
   ],
   "arl":[
      [
         "ardabil"
      ],
      0,
      0
   ],
   "bah":[
      [
         "bahmanis"
      ],
      4000,
      1105
   ],
   "cir":[
      [
         "circassia"
      ],
      0,
      0
   ],
   "com":[
      [
         "comanche"
      ],
      0,
      0
   ],
   "smo":[
      [
         "smolensk"
      ],
      3329,
      514
   ],
   "mas":[
      [
         "madyaas"
      ],
      0,
      0
   ],
   "isf":[
      [
         "isfahan"
      ],
      0,
      0
   ],
   "cow":[
      [
         "coweta"
      ],
      0,
      0
   ],
   "nvr":[
      [
         "navanagar"
      ],
      0,
      0
   ],
   "byt":[
      [
         "bayreuth"
      ],
      0,
      0
   ],
   "sib":[
      [
         "sibir"
      ],
      0,
      0
   ],
   "lei":[
      [
         "leinster"
      ],
      0,
      0
   ],
   "ere":[
      [
         "eretna"
      ],
      0,
      0
   ],
   "ade":[
      [
         "aden"
      ],
      0,
      0
   ],
   "uls":[
      [
         "ulster"
      ],
      0,
      0
   ],
   "han":[
      [
         "hanover"
      ],
      0,
      0
   ],
   "tnk":[
      [
         "taranaki"
      ],
      0,
      0
   ],
   "cad":[
      [
         "caddo"
      ],
      0,
      0
   ],
   "msi":[
      [
         "mossi"
      ],
      0,
      0
   ],
   "dam":[
      [
         "damot"
      ],
      0,
      0
   ],
   "img":[
      [
         "imagawa"
      ],
      0,
      0
   ],
   "had":[
      [
         "hadoti"
      ],
      0,
      0
   ],
   "jpr":[
      [
         "jeypore"
      ],
      0,
      0
   ],
   "smz":[
      [
         "shimazu"
      ],
      4843,
      872
   ],
   "ike":[
      [
         "ikeda"
      ],
      0,
      0
   ],
   "rig":[
      [
         "riga"
      ],
      3187,
      379
   ],
   "wcr":[
      [
         "cree"
      ],
      0,
      0
   ],
   "lpp":[
      [
         "lippe"
      ],
      0,
      0
   ],
   "tra":[
      [
         "transylvania"
      ],
      0,
      0
   ],
   "ver":[
      [
         "verden"
      ],
      0,
      0
   ],
   "zap":[
      [
         "zapotec"
      ],
      0,
      0
   ],
   "arw":[
      [
         "arawak"
      ],
      0,
      0
   ],
   "nng":[
      [
         "ning"
      ],
      0,
      0
   ],
   "sak":[
      [
         "siak"
      ],
      0,
      0
   ],
   "rjk":[
      [
         "rajkot"
      ],
      0,
      0
   ],
   "cri":[
      [
         "crimea"
      ],
      3376,
      576
   ],
   "kie":[
      [
         "kiev"
      ],
      0,
      0
   ],
   "aot":[
      [
         "aotearoa"
      ],
      0,
      0
   ],
   "mlc":[
      [
         "malacca"
      ],
      4396,
      1333
   ],
   "hod":[
      [
         "khodynt"
      ],
      0,
      0
   ],
   "ldu":[
      [
         "lundu"
      ],
      0,
      0
   ],
   "ata":[
      [
         "atahachi"
      ],
      0,
      0
   ],
   "lri":[
      [
         "luristan"
      ],
      0,
      0
   ],
   "tti":[
      [
         "tsutsui"
      ],
      0,
      0
   ],
   "smi":[
      [
         "sapmi"
      ],
      0,
      0
   ],
   "grk":[
      [
         "gorkha"
      ],
      0,
      0
   ],
   "cor":[
      [
         "corsica"
      ],
      0,
      0
   ],
   "prk":[
      [
         "perak"
      ],
      0,
      0
   ],
   "cnd":[
      [
         "candar"
      ],
      0,
      0
   ],
   "aco":[
      [
         "acoma"
      ],
      0,
      0
   ],
   "ena":[
      [
         "ennarea"
      ],
      0,
      0
   ],
   "apa":[
      [
         "apache"
      ],
      0,
      0
   ],
   "tbk":[
      [
         "tumbuka"
      ],
      0,
      0
   ],
   "bnd":[
      [
         "bundelkhand"
      ],
      0,
      0
   ],
   "mda":[
      [
         "medina"
      ],
      0,
      0
   ],
   "nol":[
      [
         "northumberland"
      ],
      0,
      0
   ],
   "avi":[
      [
         "avignon"
      ],
      0,
      0
   ],
   "que":[
      [
         "quebec"
      ],
      0,
      0
   ],
   "tla":[
      [
         "tlapanec"
      ],
      0,
      0
   ],
   "hed":[
      [
         "hejaz"
      ],
      0,
      0
   ],
   "syo":[
      [
         "soyo"
      ],
      0,
      0
   ],
   "awn":[
      [
         "awngthim"
      ],
      0,
      0
   ],
   "mdi":[
      [
         "mogadishu"
      ],
      0,
      0
   ],
   "yan":[
      [
         "yan"
      ],
      0,
      0
   ],
   "qom":[
      [
         "ajam"
      ],
      3594,
      821
   ],
   "wen":[
      [
         "wenro"
      ],
      0,
      0
   ],
   "mmi":[
      [
         "miami"
      ],
      0,
      0
   ],
   "pta":[
      [
         "patiala"
      ],
      0,
      0
   ],
   "yaq":[
      [
         "yaqui"
      ],
      0,
      0
   ],
   "chk":[
      [
         "champasak"
      ],
      0,
      0
   ],
   "flo":[
      [
         "florida"
      ],
      0,
      0
   ],
   "mgd":[
      [
         "maguindanao"
      ],
      0,
      0
   ],
   "bst":[
      [
         "bastar"
      ],
      0,
      0
   ],
   "anh":[
      [
         "anhalt"
      ],
      0,
      0
   ],
   "ama":[
      [
         "amago"
      ],
      0,
      0
   ],
   "oeo":[
      [
         "oneota"
      ],
      0,
      0
   ],
   "hse":[
      [
         "hsenwi"
      ],
      0,
      0
   ],
   "clm":[
      [
         "colima"
      ],
      0,
      0
   ],
   "cyi":[
      [
         "yi"
      ],
      0,
      0
   ],
   "asi":[
      [
         "assiniboine"
      ],
      0,
      0
   ],
   "dau":[
      [
         "dauphine"
      ],
      0,
      0
   ],
   "eic":[
      [
         "east_india_company"
      ],
      4190,
      1014
   ],
   "skk":[
      [
         "sikkim"
      ],
      0,
      0
   ],
   "sik":[
      [
         "sikh_empire"
      ],
      3955,
      830
   ],
   "ben":[
      [
         "benin"
      ],
      0,
      0
   ],
   "hja":[
      [
         "huyla"
      ],
      0,
      0
   ],
   "mri":[
      [
         "mori"
      ],
      0,
      0
   ],
   "wka":[
      [
         "wanka"
      ],
      0,
      0
   ],
   "lno":[
      [
         "lanao"
      ],
      0,
      0
   ],
   "krw":[
      [
         "karagwe"
      ],
      0,
      0
   ],
   "ceb":[
      [
         "cebu"
      ],
      0,
      0
   ],
   "lan":[
      [
         "florence"
      ],
      2987,
      654
   ],
   "frs":[
      [
         "fars"
      ],
      0,
      0
   ],
   "jgd":[
      [
         "junagarh"
      ],
      0,
      0
   ],
   "csc":[
      [
         "cascadia"
      ],
      0,
      0
   ],
   "mdy":[
      [
         "madyas"
      ],
      4718,
      1219
   ],
   "rom":[
      [
         "romanempire"
      ],
      0,
      0
   ],
   "bon":[
      [
         "bonoman"
      ],
      0,
      0
   ],
   "ilk":[
      [
         "ilkhanate"
      ],
      0,
      0
   ],
   "mlg":[
      [
         "malagana"
      ],
      0,
      0
   ],
   "ava":[
      [
         "ava"
      ],
      0,
      0
   ],
   "mfy":[
      [
         "mahafaly"
      ],
      0,
      0
   ],
   "min":[
      [
         "min"
      ],
      0,
      0
   ],
   "bla":[
      [
         "blackfoot"
      ],
      0,
      0
   ],
   "sta":[
      [
         "stadacona"
      ],
      0,
      0
   ],
   "dhu":[
      [
         "dhundhar"
      ],
      0,
      0
   ],
   "gua":[
      [
         "guarani"
      ],
      0,
      0
   ],
   "mix":[
      [
         "mixtec"
      ],
      0,
      0
   ],
   "swi":[
      [
         "switzerland"
      ],
      2943,
      586
   ],
   "dwt":[
      [
         "donauwoerth"
      ],
      0,
      0
   ],
   "lnd":[
      [
         "lunda"
      ],
      0,
      0
   ],
   "ska":[
      [
         "sakalava"
      ],
      0,
      0
   ],
   "chr":[
      [
         "chernigov"
      ],
      0,
      0
   ],
   "ill":[
      [
         "illiniwek"
      ],
      0,
      0
   ],
   "clg":[
      [
         "chalahgawtha"
      ],
      0,
      0
   ],
   "geo":[
      [
         "georgia"
      ],
      3489,
      690
   ],
   "ogs":[
      [
         "ogasawara"
      ],
      0,
      0
   ],
   "pol":[
      [
         "poland"
      ],
      3130,
      524
   ],
   "oka":[
      [
         "odoyev"
      ],
      0,
      0
   ],
   "bad":[
      [
         "baden"
      ],
      0,
      0
   ],
   "beu":[
      [
         "berau"
      ],
      0,
      0
   ],
   "#isr":[
      [
         "israel"
      ],
      0,
      0
   ],
   "kba":[
      [
         "kabylia"
      ],
      0,
      0
   ],
   "dti":[
      [
         "doti"
      ],
      0,
      0
   ],
   "ser":[
      [
         "serbia"
      ],
      3136,
      647
   ],
   "lau":[
      [
         "saxe-lauenburg",
         "saxe-lauenburg"
      ],
      0,
      0
   ],
   "mre":[
      [
         "marehan"
      ],
      0,
      0
   ],
   "cla":[
      [
         "colla"
      ],
      0,
      0
   ],
   "dte":[
      [
         "date"
      ],
      4999,
      769
   ],
   "mew":[
      [
         "mewat"
      ],
      0,
      0
   ],
   "dlh":[
      [
         "delhi",
         "india"
      ],
      4008,
      920
   ],
   "dnz":[
      [
         "danzig"
      ],
      0,
      0
   ],
   "kik":[
      [
         "kikondja"
      ],
      0,
      0
   ],
   "krk":[
      [
         "carnatic"
      ],
      0,
      0
   ],
   "kmc":[
      [
         "kamchadals"
      ],
      0,
      0
   ],
   "qic":[
      [
         "qi"
      ],
      0,
      0
   ],
   "als":[
      [
         "alsace"
      ],
      0,
      0
   ],
   "lfa":[
      [
         "lanfang"
      ],
      0,
      0
   ],
   "ldk":[
      [
         "ladakh"
      ],
      0,
      0
   ],
   "syn":[
      [
         "synthetics"
      ],
      0,
      0
   ],
   "shm":[
      [
         "shammar"
      ],
      0,
      0
   ],
   "tri":[
      [
         "trier"
      ],
      0,
      0
   ],
   "dms":[
      [
         "desmond"
      ],
      2679,
      483
   ],
   "ttl":[
      [
         "three_leagues",
         "three"
      ],
      1827,
      1034
   ],
   "tts":[
      [
         "two sicilies"
      ],
      0,
      0
   ],
   "tkg":[
      [
         "tokugawa"
      ],
      0,
      0
   ],
   "bri":[
      [
         "brittany",
         "britany"
      ],
      2770,
      569
   ],
   "hsi":[
      [
         "hsipaw"
      ],
      0,
      0
   ],
   "ter":[
      [
         "ternate"
      ],
      4798,
      1374
   ],
   "pga":[
      [
         "perugia"
      ],
      0,
      0
   ],
   "grm":[
      [
         "germiyan"
      ],
      0,
      0
   ],
   "yas":[
      [
         "yas"
      ],
      0,
      0
   ],
   "frc":[
      [
         "francia"
      ],
      2850,
      553
   ],
   "naz":[
      [
         "nizzarids"
      ],
      3277,
      904
   ],
   "jsn":[
      [
         "joseon"
      ],
      4784,
      748
   ],
   "vlt":[
      [
         "veleti"
      ],
      3012,
      472
   ],
   "obd":[
      [
         "obotrites"
      ],
      2981,
      458
   ],
   "mgy":[
      [
         "magyars"
      ],
      3135,
      595
   ],
   "arg":[
      [
         "argentina"
      ],
      1822,
      1722
   ],
   "ngr":[
      [
         "new_granada",
         "columbia",
         "grand_columbia"
      ],
      1657,
      1144
   ],
   "bol":[
      [
         "bolivia"
      ],
      1763,
      1399
   ]
}
